dqcsim_quantumsim/__init__.py
dqcsim_quantumsim/__main__.py
dqcsim_quantumsim/backend.py
dqcsim_quantumsim/qubit.py
dqcsim_quantumsim/test.py
dqcsim_quantumsim-0.0.5.data/data/bin/dqcsbequantumsim
dqcsim_quantumsim-0.0.5.dist-info/LICENSE
dqcsim_quantumsim-0.0.5.dist-info/METADATA
dqcsim_quantumsim-0.0.5.dist-info/WHEEL
dqcsim_quantumsim-0.0.5.dist-info/top_level.txt
dqcsim_quantumsim-0.0.5.dist-info/RECORD
