Metadata-Version: 2.1
Name: dqcsim-quantumsim
Version: 0.0.5
Summary: DQCsim backend for QuantumSim.
Home-page: https://github.com/QE-Lab/dqcsim-quantumsim
Author: Jeroen van Straten
Author-email: j.vanstraten-1@tudelft.nl
License: GPLv3
Keywords: dqcsim quantumsim
Platform: UNKNOWN
Classifier: Development Status :: 3 - Alpha
Classifier: Intended Audience :: Science/Research
Classifier: License :: OSI Approved :: GNU General Public License v3 (GPLv3)
Classifier: Topic :: Scientific/Engineering
Requires-Dist: dqcsim (>=0.2.0)
Requires-Dist: quantumsim (==0.2)
